<?xml version="1.0" encoding="utf-8" ?><dwsync><file name="1.gif" server="qxu1194690288.my3w.com//htdocs/" local="3482777510" remote="3535253460" Dst="-1" /><file name="10.gif" server="qxu1194690288.my3w.com//htdocs/" local="3482777510" remote="3535253460" Dst="-1" /><file name="11.gif" server="qxu1194690288.my3w.com//htdocs/" local="3482777510" remote="3535253460" Dst="-1" /><file name="12.gif" server="qxu1194690288.my3w.com//htdocs/" local="3482777510" remote="3535253460" Dst="-1" /><file name="13.gif" server="qxu1194690288.my3w.com//htdocs/" local="3482777510" remote="3535253460" Dst="-1" /><file name="14.gif" server="qxu1194690288.my3w.com//htdocs/" local="3482777510" remote="3535253460" Dst="-1" /><file name="16.gif" server="qxu1194690288.my3w.com//htdocs/" local="3482777510" remote="3535253460" Dst="-1" /><file name="15.gif" server="qxu1194690288.my3w.com//htdocs/" local="3482777510" remote="3535253460" Dst="-1" /><file name="17.gif" server="qxu1194690288.my3w.com//htdocs/" local="3482777510" remote="3535253460" Dst="-1" /><file name="18.gif" server="qxu1194690288.my3w.com//htdocs/" local="3482777510" remote="3535253460" Dst="-1" /><file name="3.gif" server="qxu1194690288.my3w.com//htdocs/" local="3482777510" remote="3535253460" Dst="-1" /><file name="19.gif" server="qxu1194690288.my3w.com//htdocs/" local="3482777510" remote="3535253460" Dst="-1" /><file name="2.gif" server="qxu1194690288.my3w.com//htdocs/" local="3482777510" remote="3535253460" Dst="-1" /><file name="20.gif" server="qxu1194690288.my3w.com//htdocs/" local="3482777510" remote="3535253460" Dst="-1" /><file name="5.gif" server="qxu1194690288.my3w.com//htdocs/" local="3482777510" remote="3535253460" Dst="-1" /><file name="6.gif" server="qxu1194690288.my3w.com//htdocs/" local="3482777510" remote="3535253460" Dst="-1" /><file name="7.gif" server="qxu1194690288.my3w.com//htdocs/" local="3482777510" remote="3535253460" Dst="-1" /><file name="4.gif" server="qxu1194690288.my3w.com//htdocs/" local="3482777510" remote="3535253460" Dst="-1" /><file name="8.gif" server="qxu1194690288.my3w.com//htdocs/" local="3482777510" remote="3535253460" Dst="-1" /><file name="9.gif" server="qxu1194690288.my3w.com//htdocs/" local="3482777510" remote="3535253460" Dst="-1" /><file name="bg.gif" server="qxu1194690288.my3w.com//htdocs/" local="3482777510" remote="3535253460" Dst="-1" /><file name="line.gif" server="qxu1194690288.my3w.com//htdocs/" local="3482777510" remote="3535253460" Dst="-1" /></dwsync>